chutoro/__init__.py
chutoro/main.py
chutoro-0.1.1.dist-info/WHEEL
chutoro-0.1.1.dist-info/METADATA
chutoro-0.1.1.dist-info/RECORD
